[
    {
        "name": "Automated Waffle Solver",
        "imageSrc": "yadda yadda",
        "description": "A Java program that can solve a game of Waffle.",
        "websiteLink": "https://github.com/thereare21/WaffleSolver"
    },

    {
        "name": "Bad Apple but it's ASCII Art",
        "imageSrc": "yadda yadda",
        "description": "Converts Bad Apple MV into ASCII animation using C++ and OpenCV and displays it in Terminal.",
        "websiteLink": "https://github.com/sepfish/BadAppleConsoleCPP"
    },

    {
        "name": "MIDI Cascader",
        "imageSrc": "yadda yadda",
        "description": "Play one note, a glissando of notes will follow.",
        "websiteLink": "https://github.com/sepfish/BadAppleConsoleCPP"
    },

    {
        "name": "Soul Solace Horror Game",
        "imageSrc": "yadda yadda",
        "description": "Psychological Horror Game made for Brackeys Game Jam 2023",
        "websiteLink": "https://github.com/sepfish/BadAppleConsoleCPP"
    },

    {
        "name": "The Roots of Yggdrasil",
        "imageSrc": "yadda yadda",
        "description": "",
        "websiteLink": "https://github.com/sepfish/BadAppleConsoleCPP"
    }
]